StreamlitCookies/__init__.py
StreamlitCookies/frontend/build/asset-manifest.json
StreamlitCookies/frontend/build/index.html
StreamlitCookies/frontend/build/precache-manifest.4918dcc529d2a5e42b384c63a33f9ab3.js
StreamlitCookies/frontend/build/service-worker.js
StreamlitCookies/frontend/build/static/js/2.5e7e6522.chunk.js
StreamlitCookies/frontend/build/static/js/2.5e7e6522.chunk.js.LICENSE.txt
StreamlitCookies/frontend/build/static/js/2.5e7e6522.chunk.js.map
StreamlitCookies/frontend/build/static/js/main.3e3766d6.chunk.js
StreamlitCookies/frontend/build/static/js/main.3e3766d6.chunk.js.map
StreamlitCookies/frontend/build/static/js/runtime-main.22c33df6.js
StreamlitCookies/frontend/build/static/js/runtime-main.22c33df6.js.map
streamkies-0.1.0.dist-info/LICENSE
streamkies-0.1.0.dist-info/METADATA
streamkies-0.1.0.dist-info/WHEEL
streamkies-0.1.0.dist-info/top_level.txt
streamkies-0.1.0.dist-info/RECORD
