Metadata-Version: 2.1
Name: streamkies
Version: 0.1.0
Summary: Cookies API for Streamlit
Home-page: UNKNOWN
Author: huanxingke
Author-email: 201930191473@mail.scut.edu.cn
License: UNKNOWN
Platform: UNKNOWN
Requires-Python: >=3.6
Requires-Dist: streamlit (>=0.63)
